pythonmonkey/__init__.py
pythonmonkey/builtin_modules/base64.d.ts
pythonmonkey/builtin_modules/base64.py
pythonmonkey/builtin_modules/console.js
pythonmonkey/builtin_modules/dom-exception.d.ts
pythonmonkey/builtin_modules/dom-exception.js
pythonmonkey/builtin_modules/event-target.js
pythonmonkey/builtin_modules/internal-binding.d.ts
pythonmonkey/builtin_modules/internal-binding.py
pythonmonkey/builtin_modules/timers.js
pythonmonkey/builtin_modules/url.d.ts
pythonmonkey/builtin_modules/url.js
pythonmonkey/builtin_modules/util.js
pythonmonkey/builtin_modules/XMLHttpRequest-internal.d.ts
pythonmonkey/builtin_modules/XMLHttpRequest-internal.py
pythonmonkey/builtin_modules/XMLHttpRequest.js
pythonmonkey/cli/__init__.py
pythonmonkey/cli/pmjs.py
pythonmonkey/global.d.ts
pythonmonkey/helpers.py
pythonmonkey/lib/pmdb.py
pythonmonkey/lib/pmjs/global-init.js
pythonmonkey/lib/wtfpm.py
pythonmonkey/mozjs-136a1.dll
pythonmonkey/pythonmonkey.pyd
pythonmonkey/pythonmonkey.pyi
pythonmonkey/require.py
pythonmonkey/tsconfig.json
pythonmonkey-1.1.1.dist-info/entry_points.txt
pythonmonkey-1.1.1.dist-info/LICENSE
pythonmonkey-1.1.1.dist-info/METADATA
pythonmonkey-1.1.1.dist-info/WHEEL
pythonmonkey-1.1.1.dist-info/RECORD
